[{"s": "2-din-magnitola-dlya-lada-granta-fl", "t": "2 DIN магнитола для Лада Гранта FL: выбор, установка, подключение", "i": "📁", "c": "granta"}, {"s": "2-din-magnitola-lada-granta", "t": "2 DIN магнитола Лада Гранта: выбор, установка, прошивка", "i": "📁", "c": "granta"}, {"s": "2-din-magnitola-lada-vesta", "t": "2 дин магнитола Лада Веста: выбор, установка, настройка", "i": "📁", "c": "vesta"}, {"s": "2-din-magnitola-dlya-lada-granta", "t": "2 Din магнитола для Лада Гранта: выбор, установка и настройка", "i": "📁", "c": "granta"}, {"s": "2-to-lada-granta", "t": "2 ТО Лада Гранта: цена, список работ и регламент замены", "i": "📁", "c": "granta"}]