[{"s": "panel-priborov-lada-granta-oboznacheniya", "t": "Обозначения панели приборов Лада Гранта: расшифровка всех значков", "i": "📁", "c": "granta"}, {"s": "panel-priborov-lada-vesta-sv-kross", "t": "Панель приборов Lada Vesta SW Cross: устройство, сброс ошибок, тюнинг", "i": "📁", "c": "vesta"}, {"s": "panel-priborov-lada-niva-trevel", "t": "Панель приборов Lada Niva Travel: устройство, неисправности, тюнинг", "i": "📁", "c": "niva-travel"}, {"s": "parametry-diskov-lada-largus", "t": "Диски на Лада Ларгус: размеры, параметры, выбор и установка", "i": "📁", "c": "largus"}, {"s": "parktronik-lada-granta-liftbek", "t": "Парктроник на Лада Гранта Лифтбек: выбор, установка, настройка", "i": "📁", "c": "granta"}, {"s": "patrubki-otopitelya-lada-vesta", "t": "Патрубки отопителя Lada Vesta: замена, неисправности, артикулы", "i": "📁", "c": "vesta"}, {"s": "patrubki-radiatora-lada-granta", "t": "Патрубки радиатора Лада Гранта: выбор, замена, диагностика", "i": "📁", "c": "granta"}, {"s": "palatka-na-kryshu-lada-vesta", "t": "Палатка на крышу Lada Vesta: выбор, установка и советы 2026", "i": "📁", "c": "vesta"}, {"s": "patron-povorotnika-lada-granta", "t": "Патрон поворотника Лада Гранта: замена, выбор, неисправности", "i": "📁", "c": "granta"}, {"s": "panel-lada-kh-rej", "t": "Панель приборов Lada XRAY: особенности, неисправности, замена", "i": "📁", "c": "xray"}, {"s": "panel-priborov-lada-vesta-oboznachenie", "t": "Панель приборов Lada Vesta: расшифровка всех значков и индикаторов", "i": "📁", "c": "vesta"}, {"s": "panel-upravleniya-lada-granta-sedan", "t": "Панель управления Lada Granta Sedan: функции, настройки и ремонт", "i": "📁", "c": "granta"}, {"s": "parametry-diskov-lada-largus-r15", "t": "Диски R15 на Лада Ларгус: параметры, размеры и выбор 2026", "i": "📁", "c": "largus"}, {"s": "parktroniki-dlya-lada-granta", "t": "Парктроники для Лада Гранта: выбор, установка, настройка (2026)", "i": "📁", "c": "granta"}, {"s": "panel-predokhranitelej-lada-kalina", "t": "Блок предохранителей Лада Калина: схема, расположение, замена", "i": "📁", "c": "kalina"}, {"s": "parametry-diskov-lada-granta-r14", "t": "Диски R14 на Лада Гранта: параметры, размеры и выбор (2026)", "i": "📁", "c": "granta"}, {"s": "panel-lada-granta-2015", "t": "Панель Лада Гранта 2015: особенности, ремонт и тюнинг", "i": "📁", "c": "granta"}, {"s": "patrubki-sistemy-okhlazhdeniya-lada-kalina", "t": "Патрубки охлаждения Лада Калина: замена, диагностика, выбор", "i": "📁", "c": "kalina"}, {"s": "parametry-koles-lada-granta", "t": "Размеры и параметры колес Lada Granta: таблицы и рекомендации", "i": "📁", "c": "granta"}, {"s": "patrubok-pechki-lada-largus", "t": "Патрубок печки Лада Ларгус: замена, неисправности, артикулы", "i": "📁", "c": "largus"}, {"s": "parametry-akkumulyatora-lada-vesta", "t": "Аккумулятор Лада Веста: параметры, выбор, замена (2026)", "i": "📁", "c": "vesta"}, {"s": "parktroniki-lada-granta", "t": "Парктроники на Лада Гранта: выбор, установка, настройка 2026", "i": "📁", "c": "granta"}, {"s": "pauk-lada-granta-8-klapanov", "t": "Паук на Лада Гранта 8 клапанов: установка, выбор и отзывы", "i": "📁", "c": "granta"}, {"s": "panoramnaya-krysha-lada-vesta", "t": "Панорамная крыша на Lada Vesta: плюсы, минусы и установка", "i": "📁", "c": "vesta"}, {"s": "parametry-diska-lada-vesta", "t": "Размеры и параметры дисков Lada Vesta: таблица совместимости", "i": "📁", "c": "vesta"}, {"s": "parametry-diska-lada-granta", "t": "Параметры дисков Lada Granta: размеры, разболтовка, вылет ET", "i": "📁", "c": "granta"}, {"s": "patrubki-radiatora-lada-largus", "t": "Патрубки радиатора Lada Largus: выбор, замена, неисправности", "i": "📁", "c": "largus"}, {"s": "panel-priborov-lada-vesta-kross", "t": "Панель приборов Lada Vesta Cross: функции, неисправности, тюнинг", "i": "📁", "c": "vesta"}, {"s": "parametry-diskov-dlya-lada-vesta", "t": "Диски на Лада Веста: параметры, размеры, подбор 2026", "i": "📁", "c": "vesta"}, {"s": "patrubki-pechki-lada-granta", "t": "Патрубки печки Лада Гранта: замена, неисправности, выбор запчастей", "i": "📁", "c": "granta"}, {"s": "patrubok-radiatora-lada-largus", "t": "Патрубок радиатора Лада Ларгус: выбор, замена, неисправности", "i": "📁", "c": "largus"}, {"s": "panel-lada-largus-opisanie", "t": "Панель приборов Lada Largus: описание, особенности и ремонт", "i": "📁", "c": "largus"}, {"s": "panel-priborov-lada-granta-kross", "t": "Панель приборов Lada Granta Cross: устройство, неисправности, тюнинг", "i": "📁", "c": "granta"}, {"s": "panel-priborov-lada-largus", "t": "Панель приборов Lada Largus: расшифровка, неисправности, замена", "i": "📁", "c": "largus"}, {"s": "parametry-shin-lada-granta", "t": "Размеры и параметры шин Lada Granta: таблица, рекомендации, ошибки выбора", "i": "📁", "c": "granta"}, {"s": "parametry-skhod-razvala-lada-vesta", "t": "Сход-развал Лада Веста: параметры, регулировка, советы эксперта", "i": "📁", "c": "vesta"}, {"s": "parametry-gruzovogo-otseka-lada-largus-furgon", "t": "Габариты и объём грузового отсека Lada Largus фургон: полный разбор", "i": "📁", "c": "largus"}, {"s": "parametry-shin-lada-vesta", "t": "Параметры шин Lada Vesta: размеры, давление, сезонность 2026", "i": "📁", "c": "vesta"}, {"s": "parktroniki-lada-vesta-zadnie", "t": "Парктроники на Лада Веста: выбор, установка и настройка задних датчиков", "i": "📁", "c": "vesta"}, {"s": "patrubok-sapuna-lada-vesta", "t": "Патрубок сапуна Лада Веста: замена, чистка, признаки неисправности", "i": "📁", "c": "vesta"}, {"s": "panel-predokhranitelej-lada-priora", "t": "Блок предохранителей Лада Приора: схема, расположение, замена", "i": "📁", "c": "priora"}, {"s": "panel-upravleniya-lada-kalina-1", "t": "Панель управления Лада Калина 1: схема, ремонт, замена и неисправности", "i": "📁", "c": "kalina"}, {"s": "parktroniki-lada-vesta-ng", "t": "Парктроники на Лада Веста НГ: выбор, установка и настройка 2026", "i": "📁", "c": "vesta"}, {"s": "patron-zadnego-fonarya-lada-vesta", "t": "Патрон заднего фонаря Lada Vesta: выбор, замена, ошибки", "i": "📁", "c": "vesta"}, {"s": "panel-priborov-lada-kh-rej-kross-s-oboznacheniyami", "t": "Панель приборов Lada XRAY Cross: расшифровка значков и индикаторов", "i": "📁", "c": "xray"}, {"s": "panel-priborov-lada-vesta-tyuning", "t": "Тюнинг панели приборов Лада Веста: 10 идей с фото и ценами 2026", "i": "📁", "c": "vesta"}, {"s": "panel-upravleniya-lada-kalina", "t": "Панель управления Лада Калина: функции, сброс и ремонт", "i": "📁", "c": "kalina"}, {"s": "parametry-bagazhnika-lada-largus", "t": "Габариты багажника Lada Largus: объём, размеры, полезные советы", "i": "📁", "c": "largus"}, {"s": "pauk-lada-vesta-16", "t": "Паук на Лада Веста 1.6: схема, установка и тюнинг выхлопа", "i": "📁", "c": "vesta"}, {"s": "parametry-diskov-lada-granta-r15", "t": "Диски R15 на Лада Гранта: параметры, размеры и выбор 2026", "i": "📁", "c": "granta"}, {"s": "panel-upravleniya-na-lada-granta", "t": "Панель управления Лада Гранта: устройство, ошибки и доработка", "i": "📁", "c": "granta"}, {"s": "patrubki-pechki-lada-kalina", "t": "Патрубки печки Лада Калина: размеры, замена, схема", "i": "📁", "c": "kalina"}, {"s": "panel-priborov-lada-granta-opisanie", "t": "Панель приборов Лада Гранта: полное описание, значки и ремонт", "i": "📁", "c": null}, {"s": "panel-priborov-lada-kalina-1-opisanie-lamp-i-indikatorov", "t": "Панель приборов Лада Калина 1: расшифровка ламп и индикаторов", "i": "📁", "c": "kalina"}, {"s": "parktronik-na-lada-granta", "t": "Парктроник на Лада Гранта: выбор, установка своими руками, схемы", "i": "📁", "c": "granta"}, {"s": "palitra-tsvetov-lada-granta", "t": "Палитра цветов Лада Гранта 2026: коды и фото оттенков", "i": "📁", "c": "granta"}, {"s": "panel-lada-kalina-1", "t": "Панель Лада Калина 1: Ремонт, разборка и тюнинг своими руками", "i": "📁", "c": "kalina"}, {"s": "panel-priborov-lada-priora", "t": "Панель приборов Лада Приора: устройство, разборка и тюнинг", "i": "📁", "c": "priora"}, {"s": "patrubki-na-lada-granta-8-klapannaya", "t": "Патрубки Лада Гранта 8 клапанная: размеры, артикулы, замена", "i": "📁", "c": "granta"}, {"s": "parametry-diskov-lada-kh-rej", "t": "Параметры дисков Лада Х-Рей: размеры, вылет и сверловка", "i": "📁", "c": "xray"}, {"s": "panel-priborov-lada-kalina", "t": "Панель приборов Лада Калина: устройство, датчики и доработки", "i": "📁", "c": "kalina"}, {"s": "pakhnet-benzinom-v-salone-lada-granta", "t": "Почему в салоне Лада Гранта пахнет бензином: причины и устранение", "i": "📁", "c": "granta"}, {"s": "panel-priborov-lada-kh-rej-s-oboznacheniyami", "t": "Панель приборов Лада XRAY: обозначения и расшифровка", "i": "📁", "c": "xray"}, {"s": "paradnaya-anfilada-tverskogo-imperatorskogo-dvortsa", "t": "Парадная анфилада Тверского императорского дворца: История", "i": "📁", "c": "drugoe"}, {"s": "parametry-koles-lada-vesta", "t": "Параметры колес Лада Веста: размеры, диски, шины", "i": "📁", "c": "vesta"}, {"s": "parktronik-lada-granta", "t": "Парктроник Лада Гранта: установка, схема подключения и настройка", "i": "📁", "c": "granta"}, {"s": "patrubok-radiatora-lada-vesta", "t": "Патрубок радиатора Лада Веста: замена, артикулы и советы", "i": "📁", "c": "vesta"}, {"s": "panel-priborov-lada-kalina-1", "t": "Панель приборов Лада Калина 1: виды, ремонт и тюнинг", "i": "📁", "c": null}, {"s": "parametry-diskov-lada-vesta-sport", "t": "Параметры дисков Лада Веста Спорт: размеры, вылет и сверловка", "i": "📁", "c": "vesta"}, {"s": "parol-ot-magnitoly-lada-largus", "t": "Пароль от магнитолы Лада Ларгус: сброс и ввод кода", "i": "📁", "c": "largus"}, {"s": "panel-upravleniya-lada-granta", "t": "Панель управления Лада Гранта: устройство, кнопки и доработка", "i": "📁", "c": "granta"}, {"s": "panel-upravleniya-lada-kh-rej", "t": "Панель управления Лада Х-Рей: функции, ошибки и настройка", "i": "📁", "c": "xray"}, {"s": "parktronik-lada-largus", "t": "Парктроник Лада Ларгус: выбор, установка и настройка своими руками", "i": "📁", "c": "largus"}, {"s": "parktroniki-na-lada-granta-liftbek", "t": "Парктроники на Лада Гранта лифтбек: установка и настройка", "i": "📁", "c": "granta"}, {"s": "palitra-tsvetov-lada", "t": "Палитра цветов Лада: коды, названия и подбор краски", "i": "📁", "c": "drugoe"}, {"s": "parametry-koles-lada-priora", "t": "Параметры колес Лада Приора: размеры, вылет и совместимость", "i": "📁", "c": "priora"}, {"s": "parktroniki-lada-granta-liftbek", "t": "Парктроники Лада Гранта Лифтбек: выбор, установка и настройка", "i": "📁", "c": "granta"}, {"s": "patrubok-vozdushnogo-filtra-lada-vesta", "t": "Патрубок воздушного фильтра Лада Веста: выбор и замена", "i": "📁", "c": "vesta"}, {"s": "parus-lada-kazan-ofitsialnyj-sajt", "t": "Парус Лада Казань: официальный сайт, цены, отзывы и автосалон", "i": "📁", "c": "drugoe"}, {"s": "pallada-i-nadezhda", "t": "Паллада и Надежда: история, мифы и связь имен", "i": "📁", "c": "drugoe"}, {"s": "parametry-koles-lada-kalina", "t": "Параметры колес Лада Калина: размеры, вылет и давление", "i": "📁", "c": "kalina"}, {"s": "parametry-diskov-lada-granta-fl", "t": "Параметры дисков Лада Гранта ФЛ: размеры, вылет, сверловка и совместимость", "i": "📁", "c": "granta"}, {"s": "parametry-lada-vesta-sv-kross", "t": "Параметры Лада Веста СВ Кросс: Габариты, клиренс, двигатели", "i": "📁", "c": "vesta"}, {"s": "panel-lada-iskra", "t": "Панель Лада Искра: обзор, характеристики и сравнение с Вестой", "i": "📁", "c": null}, {"s": "parametry-diskov-lada-vesta-sv-kross-r17", "t": "Параметры дисков Лада Веста SW Кросс R17: полный обзор и размеры", "i": "📁", "c": "vesta"}, {"s": "patrubki-pechki-lada-largus", "t": "Патрубки печки Лада Ларгус: замена, размеры, схема", "i": "📁", "c": "largus"}, {"s": "pavlik-narkoman-lada-kalina", "t": "Павлик и наркоман: разбор сленга про Лада Калина", "i": "📁", "c": "kalina"}, {"s": "parktronik-lada-granta-shtatnyj", "t": "Парктроник Лада Гранта штатный: выбор, установка и настройка", "i": "📁", "c": "granta"}, {"s": "panel-lada-iks-rej", "t": "Панель Лада Икс Рей: устройство, датчики и тюнинг", "i": "📁", "c": "xray"}, {"s": "patrubki-lada-granta", "t": "Патрубки Лада Гранта: артикулы, замена и устранение течей", "i": "📁", "c": "granta"}, {"s": "panel-priborov-lada-granta-fl-znacheniya-kombinatsiya", "t": "Панель приборов Лада Гранта ФЛ: расшифровка значков и кодов ошибок", "i": "📁", "c": "granta"}, {"s": "panel-priborov-na-lada-vesta", "t": "Панель приборов Лада Веста: виды, ошибки и ремонт", "i": "📁", "c": "vesta"}, {"s": "panel-upravleniya-lada-vesta", "t": "Панель управления Лада Веста: функции, кнопки и настройки", "i": "📁", "c": "vesta"}, {"s": "panel-lada-vesta-kross", "t": "Панель Лада Веста Кросс: обзор, характеристики и установка", "i": "📁", "c": "vesta"}, {"s": "panel-priborov-lada-granta-opisanie-i-oboznacheniya-znachkov", "t": "Панель приборов Лада Гранта: расшифровка значков и описание", "i": "📁", "c": "granta"}, {"s": "parusnik-pallada-vladivostok", "t": "Парусник Паллада во Владивостоке: история, экскурсии и факты", "i": "📁", "c": "drugoe"}, {"s": "panel-priborov-lada-iks-rej", "t": "Панель приборов Лада Икс Рей: виды, ошибки и доработка", "i": "📁", "c": "xray"}, {"s": "parametry-diskov-lada-vesta", "t": "Параметры дисков Лада Веста: размеры, вылет, сверловка", "i": "📁", "c": "vesta"}, {"s": "parus-kazan-lada", "t": "Парус Казань Лада: цены, комплектации и выбор авто в наличии", "i": "📁", "c": null}, {"s": "patrubok-sapuna-lada-granta-8-klapannaya", "t": "Патрубок сапуна Лада Гранта 8 клапанная: замена и диагностика", "i": "📁", "c": "granta"}, {"s": "parametry-diskov-lada-vesta-r17", "t": "Параметры дисков Лада Веста R17: размеры, вылет и сверловка", "i": "📁", "c": "vesta"}, {"s": "pallada-bronepalubnyj-krejser", "t": "Бронепалубный крейсер «Паллада»: история гибели и ТТХ", "i": "📁", "c": null}, {"s": "panel-priborov-lada-vesta", "t": "Панель приборов Lada Vesta: коды ошибок и тюнинг", "i": "📁", "c": "vesta"}, {"s": "patrubki-lada-vesta-16", "t": "Патрубки Лада Веста 1.6: замена, размеры, артикулы и нюансы", "i": "📁", "c": "vesta"}, {"s": "parnas-pragmatika-lada", "t": "Парнас Прагматика Лада: Прагматичный выбор или скрытый риск?", "i": "📁", "c": "drugoe"}, {"s": "panel-dlya-magnitoly-lada-granta", "t": "Панель для магнитолы Лада Гранта: установка, размеры, выбор", "i": "📁", "c": "granta"}, {"s": "parametry-lada-granta-universal", "t": "Параметры Лада Гранта универсал: габариты, вес, объем багажника", "i": "📁", "c": "granta"}, {"s": "pallada-parusnik-vladivostok", "t": "Парусник Паллада во Владивостоке: расписание и фото", "i": "📁", "c": "drugoe"}, {"s": "parametry-diskov-lada-kalina", "t": "Параметры дисков Лада Калина: размеры, вылет и разболтовка", "i": "📁", "c": "kalina"}, {"s": "parktronik-lada-vesta-original", "t": "Парктроник Лада Веста оригинал: артикулы, установка, цена", "i": "📁", "c": "vesta"}, {"s": "panel-priborov-lada-priora-opisanie-znachkov", "t": "Панель приборов Лада Приора: расшифровка значков и индикаторов", "i": "📁", "c": "priora"}, {"s": "parametry-diska-lada-granta-r14", "t": "Параметры диска Лада Гранта R14: размеры, вылет, сверловка", "i": "📁", "c": "granta"}, {"s": "parametry-diskov-na-lada-vesta", "t": "Параметры дисков Лада Веста: размеры, вылет, сверловка", "i": "📁", "c": "vesta"}, {"s": "palets-supporta-lada-vesta", "t": "Палец суппорта Лада Веста: признаки износа, замена и смазка", "i": "📁", "c": "vesta"}, {"s": "panel-priborov-lada-granta-liftbek", "t": "Панель приборов Лада Гранта Лифтбек: обзор, тюнинг, ошибки", "i": "📁", "c": "granta"}, {"s": "panel-priborov-lada-kalina-universal", "t": "Панель приборов Лада Калина универсал: устройство, разборка, доработка", "i": "📁", "c": null}, {"s": "parametry-lada-vesta-kross-universal", "t": "Параметры Лада Веста Кросс Универсал: размеры и характеристики", "i": "📁", "c": "vesta"}, {"s": "patrubki-lada-granta-8-kl", "t": "Патрубки Лада Гранта 8 кл: замена, артикулы и схема", "i": "📁", "c": "granta"}, {"s": "parktronik-lada-vesta", "t": "Парктроник Лада Веста: установка, настройка и выбор", "i": "📁", "c": "vesta"}, {"s": "parametry-diskov-lada", "t": "Параметры дисков Лада: размеры, вылет, разболтовка и совместимость", "i": "📁", "c": "drugoe"}, {"s": "patron-lampy-dkho-lada-granta", "t": "Патрон лампы ДХО Лада Гранта: замена и выбор", "i": "📁", "c": "granta"}, {"s": "parametry-kolesnykh-diskov-lada-granta", "t": "Параметры колесных дисков Лада Гранта: размеры, сверловка и вылет", "i": "📁", "c": "granta"}, {"s": "panel-predokhranitelej-lada-vesta-kross", "t": "Панель предохранителей Лада Веста Кросс: схемы и блоки", "i": "📁", "c": "vesta"}, {"s": "patrubki-okhlazhdeniya-lada-granta", "t": "Патрубки охлаждения Лада Гранта: замена, размеры и выбор", "i": "📁", "c": "granta"}, {"s": "patrubok-radiatora-verkhnij-lada-largus-16-klapanov", "t": "Патрубок радиатора верхний Лада Ларгус 16 клапанов: выбор и замена", "i": "📁", "c": "largus"}, {"s": "parametry-diskov-lada-vesta-r15", "t": "Параметры дисков Лада Веста R15: штатные размеры, вылет и сверловка", "i": "📁", "c": "vesta"}, {"s": "parametry-lada-largus-furgon", "t": "Параметры Лада Ларгус Фургон: технические характеристики", "i": "📁", "c": "largus"}, {"s": "partizana-zheleznyaka-lada-tsentr", "t": "Партизана Железняка Лада Центр: адрес, телефоны и услуги", "i": "📁", "c": "drugoe"}, {"s": "patrubok-benzobaka-lada-granta", "t": "Замена патрубка бензобака Лада Гранта: причины, выбор и установка", "i": "📁", "c": "granta"}, {"s": "parametry-diskov-lada-kalina-1", "t": "Параметры дисков Лада Калина 1: размеры, сверловка, вылет", "i": "📁", "c": "kalina"}, {"s": "parametry-diskov-lada-vesta-sv-kross", "t": "Параметры дисков Лада Веста SW Кросс: размеры, вылет, PCD", "i": "📁", "c": "vesta"}, {"s": "patron-dkho-lada-vesta", "t": "Патрон ДХО Лада Веста: замена, артикулы, установка LED", "i": "📁", "c": "vesta"}, {"s": "patron-stop-signala-lada-vesta", "t": "Патрон стоп-сигнала Лада Веста: замена, артикулы, неисправности", "i": "📁", "c": "vesta"}, {"s": "parametry-diskov-lada-priora", "t": "Параметры дисков Лада Приора: размеры, вылет, сверловка", "i": "📁", "c": "priora"}, {"s": "passat-b5-obem-khladagenta", "t": "Volkswagen Passat B5: объем хладагента, нормы заправки и типы фреона", "i": "📁", "c": "drugoe"}, {"s": "parametry-diskov-lada-granta", "t": "Параметры дисков Лада Гранта: размеры, вылет и совместимость", "i": "📁", "c": "granta"}, {"s": "patrubki-lada-granta-16-klapannaya", "t": "Патрубки Лада Гранта 16 клапанная: замена, артикулы, установка", "i": "📁", "c": "granta"}, {"s": "panel-lada-kalina-2", "t": "Панель Лада Калина 2: замена, разборка и установка", "i": "📁", "c": "kalina"}, {"s": "parametry-gruzovogo-otseka-lada-largus", "t": "Параметры грузового отсека Лада Ларгус: размеры, объём и схемы", "i": "📁", "c": "largus"}, {"s": "patron-lampy-lada-vesta", "t": "Патрон лампы Лада Веста: типы цоколей, замена и ремонт", "i": "📁", "c": "vesta"}, {"s": "parkovka-gusarskaya-ballada-platnaya", "t": "Парковка Гусарская Баллада: тарифы, способы оплаты и правила", "i": "📁", "c": "drugoe"}, {"s": "patrubok-rasshiritelnogo-bachka-lada-vesta", "t": "Патрубок расширительного бачка Лада Веста: замена и выбор", "i": "📁", "c": "vesta"}, {"s": "pauk-lada-granta", "t": "Паук лада гранта: виды, установка, влияние на мощность и звук", "i": "📁", "c": "granta"}, {"s": "parnas-lada-sankt-peterburg", "t": "Парнас Лада Санкт-Петербург: цены, наличие и отзывы 2026", "i": "📁", "c": "drugoe"}, {"s": "panel-lada-granta-kross", "t": "Панель Лада Гранта Кросс: характеристики, доработка и замена", "i": "📁", "c": "granta"}, {"s": "panel-predokhranitelej-lada-kalina-2", "t": "Панель предохранителей Лада Калина 2: схемы, блоки, расшифровка", "i": "📁", "c": "kalina"}, {"s": "panel-priborov-lada-vesta-ng", "t": "Панель приборов Лада Веста NG: обзор, ошибки и тюнинг", "i": "📁", "c": "vesta"}, {"s": "panel-lada-largus", "t": "Панель Лада Ларгус: устройство, ремонт, замена и тюнинг", "i": "📁", "c": "largus"}, {"s": "panel-priborov-lada-priora-1", "t": "Панель приборов Лада Приора 1: схемы, коды ошибок и тюнинг", "i": "📁", "c": "priora"}, {"s": "patrubki-pechki-lada-granta-8-klapannaya", "t": "Замена патрубков печки Лада Гранта 8 клапанов: схема, размеры, артикулы", "i": "📁", "c": "granta"}, {"s": "panel-predokhranitelej-lada-granta", "t": "Панель предохранителей Лада Гранта: схемы, фото, замена", "i": "📁", "c": "granta"}, {"s": "panel-upravleniya-lada-largus", "t": "Панель управления Лада Ларгус: устройство, кнопки и ошибки", "i": "📁", "c": "largus"}, {"s": "pasport-lada-granta", "t": "Паспорт Лада Гранта: расшифровка VIN, категории и дубликат ПТС", "i": "📁", "c": "granta"}, {"s": "panel-predokhranitelej-lada-largus", "t": "Панель предохранителей Лада Ларгус: схемы, блоки и замена", "i": "📁", "c": null}, {"s": "parametry-diskov-lada-vesta-kross", "t": "Параметры дисков Лада Веста Кросс: размеры, вылет, сверловка", "i": "📁", "c": "vesta"}, {"s": "parametry-reziny-lada-vesta", "t": "Параметры резины Лада Веста: размеры, давление, сезонность", "i": "📁", "c": "vesta"}, {"s": "parktronik-na-lada-vesta", "t": "Парктроник на Лада Веста: выбор, установка и настройка", "i": "📁", "c": "vesta"}, {"s": "parametry-lada-granta-liftbek", "t": "Параметры Лада Гранта Лифтбек: размеры, клиренс, двигатели", "i": "📁", "c": "granta"}, {"s": "patron-lampy-stop-signala-lada-vesta", "t": "Патрон лампы стоп-сигнала Лада Веста: замена и выбор", "i": "📁", "c": "vesta"}, {"s": "panel-lada-priora", "t": "Панель Лада Приора: обзор, тюнинг и замена торпедо", "i": "📁", "c": "priora"}, {"s": "parketnik-ot-lada", "t": "Паркетник от Лада: Обзор Lada XRAY Cross и технические особенности", "i": "📁", "c": "xray"}, {"s": "patron-zadnego-stop-signala-lada-vesta", "t": "Патрон заднего стоп-сигнала Лада Веста: замена и артикулы", "i": "📁", "c": "vesta"}, {"s": "parus-avtosalon-v-kazani-tseny-na-mashiny-lada", "t": "Парус Автосалон Казань: актуальные цены на Лада и наличие", "i": "📁", "c": "drugoe"}, {"s": "panel-priborov-lada-granta-tyuning", "t": "Тюнинг панели приборов Лада Гранта: замена, подсветка, установка", "i": "📁", "c": "granta"}, {"s": "panel-priborov-lada-largus-oboznacheniya-znachkov-na-pribornoj-paneli", "t": "Панель приборов Лада Ларгус: расшифровка значков и индикаторов", "i": "📁", "c": "largus"}, {"s": "patrubok-rasshiritelnogo-bachka-lada-granta", "t": "Патрубок расширительного бачка Лада Гранта: замена, артикулы, ремонт", "i": "📁", "c": "granta"}, {"s": "patrubok-vozdushnogo-filtra-lada-priora", "t": "Патрубок воздушного фильтра Лада Приора: выбор, замена и тюнинг", "i": "📁", "c": "priora"}, {"s": "pauk-lada-vesta", "t": "Паук Лада Веста: установка, типы и влияние на мощность двигателя", "i": "📁", "c": "vesta"}, {"s": "partizana-zheleznyaka-25-lada-tsentr", "t": "Лада Центр на Железняка 25: услуги, цены и отзывы клиентов", "i": "📁", "c": "largus"}, {"s": "panel-priborov-lada-granta-fl", "t": "Панель приборов Лада Гранта ФЛ: индикаторы, неисправности, ремонт", "i": "📁", "c": "granta"}, {"s": "panel-priborov-lada-iks-rej-s-opisaniem", "t": "Панель приборов Лада Икс Рей: описание, ошибки, индикаторы", "i": "📁", "c": "xray"}, {"s": "pauk-na-lada-vesta-16", "t": "Паук на Лада Веста 1.6: выбор, установка и прирост мощности", "i": "📁", "c": "vesta"}, {"s": "panel-lada-granta-fl", "t": "Панель Лада Гранта ФЛ: виды, тюнинг, доработки", "i": "📁", "c": "granta"}, {"s": "parametry-koles-lada-largus", "t": "Параметры колес Лада Ларгус: размеры, вылет и давление", "i": "📁", "c": "largus"}, {"s": "pallada-i-nadezhda-vladivostok", "t": "Паллада и Надежда Владивосток: история фрегатов", "i": "📁", "c": "drugoe"}, {"s": "panel-priborov-na-lada-kh-rej", "t": "Панель приборов Лада XRAY: тюнинг, ошибки и доработки", "i": "📁", "c": "xray"}, {"s": "panel-priborov-lada-kh-rej", "t": "Панель приборов Лада Х Рей: характеристики, ошибки и тюнинг", "i": "📁", "c": "xray"}, {"s": "pauk-lada-granta-16-klapannaya", "t": "Паук Лада Гранта 16 клапанная: выбор, установка, плюсы и минусы", "i": "📁", "c": "granta"}, {"s": "parametry-lada-vesta-sedan", "t": "Параметры Лада Веста Седан: Габариты, Двигатели, Расход", "i": "📁", "c": "vesta"}, {"s": "pallada-sudno-vladivostok", "t": "Паллада судно Владивосток: история, фото и где посмотреть", "i": "📁", "c": "drugoe"}, {"s": "panel-predokhranitelej-lada-kalina-1", "t": "Панель предохранителей Лада Калина 1: схемы, расшифровка, замена", "i": "📁", "c": "kalina"}, {"s": "parus-lada-kazan", "t": "Парус Лада Казань: официальный дилер, цены и отзывы", "i": "📁", "c": "drugoe"}, {"s": "panel-priborov-lada-priora-oboznachenie", "t": "Обозначения на панели приборов Лада Приора: расшифровка индикаторов", "i": "📁", "c": "priora"}, {"s": "panel-priborov-lada-largus-oboznacheniya", "t": "Панель приборов Лада Ларгус: расшифровка значков и обозначений", "i": "📁", "c": "largus"}, {"s": "parktroniki-na-lada-vesta", "t": "Парктроники на Лада Веста: установка и обзор систем", "i": "📁", "c": "vesta"}, {"s": "patrubki-pechki-lada-vesta", "t": "Патрубки печки Лада Веста: замена, артикулы, ремонт", "i": "📁", "c": "vesta"}, {"s": "pallada-fregat-uchebnyj", "t": "Фрегат «Паллада»: учебный парусник, ставший легендой", "i": "📁", "c": "drugoe"}, {"s": "parametry-lada-vesta", "t": "Параметры Лада Веста: размеры, клиренс, двигатели и технические характеристики", "i": "📁", "c": "vesta"}, {"s": "parametry-kuzova-lada-largus", "t": "Параметры кузова Лада Ларгус: размеры, клиренс и геометрия", "i": "📁", "c": "largus"}, {"s": "pauk-na-lada-granta-8-klapannaya", "t": "Паук 4-2-1 на Лада Гранта 8 клапанов: установка и эффект", "i": "📁", "c": "granta"}, {"s": "pallada-korabl-vladivostok", "t": "Паллада корабль Владивосток: история, адрес и режим работы", "i": "📁", "c": "drugoe"}, {"s": "panel-upravleniya-avtomobilya-lada-granta", "t": "Панель управления Лада Гранта: устройство, кнопки и функции", "i": "📁", "c": "granta"}, {"s": "patrubok-lada-granta", "t": "Патрубок Лада Гранта: замена, артикулы, выбор и установка", "i": "📁", "c": "granta"}, {"s": "paradnaya-anfilada-ekaterininskogo-dvortsa", "t": "Парадная анфилада Екатерининского дворца: история и архитектура", "i": "📁", "c": "drugoe"}, {"s": "parametry-diskov-lada-vesta-r16", "t": "Параметры дисков Лада Веста R16: размеры, вылет и совместимость", "i": "📁", "c": "vesta"}, {"s": "parametry-diskov-na-lada-granta", "t": "Параметры дисков Лада Гранта: размеры, вылет, сверловка", "i": "📁", "c": "granta"}, {"s": "parnas-lada-pragmatika", "t": "Лада Прагматика: Почему концепт не стал серийным?", "i": "📁", "c": "vesta"}]