[{"s": "zimnyaya-rezina-lada-largus", "t": "Зимняя резина для Lada Largus: выбор, размеры, советы 2026", "i": "📁", "c": "largus"}, {"s": "zimnyaya-rezina-lada-vesta", "t": "Зимняя резина для Lada Vesta: выбор, размеры, отзывы 2026", "i": "📁", "c": "vesta"}, {"s": "zimnyaya-zashchita-radiatora-lada-granta-fl", "t": "Зимняя защита радиатора Лада Гранта ФЛ: как уберечь двигатель от холода", "i": "📁", "c": "granta"}, {"s": "zimnyaya-rezina-na-lada-vesta-kross", "t": "Зимняя резина на Lada Vesta Cross: выбор, размеры, отзывы 2026", "i": "📁", "c": "vesta"}, {"s": "zimnie-kolesa-na-lada-granta-kross", "t": "Зимние колеса на Lada Granta Cross: выбор, размеры, советы 2026", "i": "📁", "c": "granta"}, {"s": "zimnie-dvorniki-dlya-avtomobilya-lada-vesta", "t": "Зимние дворники для Лада Веста: как выбрать и установить", "i": "📁", "c": "vesta"}, {"s": "zimnyaya-rezina-lada-granta", "t": "Зимняя резина для Лада Гранта: выбор, размеры, советы 2026", "i": "📁", "c": "granta"}, {"s": "zimnie-shiny-lada-granta", "t": "Зимние шины на Лада Гранта: выбор, размеры, рейтинг 2026", "i": "📁", "c": "granta"}, {"s": "zimnyaya-rezina-na-lada-granta", "t": "Зимняя резина на Лада Гранта: выбор, размеры, советы 2026", "i": "📁", "c": "granta"}, {"s": "zimnij-rezhim-dvornikov-lada-vesta", "t": "Зимний режим дворников Лада Веста: как включить и настроить", "i": "📁", "c": "vesta"}, {"s": "zimnyaya-rezina-na-lada-vesta-sv-kross-17", "t": "Зимняя резина на Лада Веста SW Кросс R17: выбор и тесты", "i": "📁", "c": "vesta"}, {"s": "zimnyaya-rezina-lada-vesta-sv-kross-r17", "t": "Зимняя резина Лада Веста SW Кросс R17: выбор и тесты", "i": "📁", "c": "vesta"}, {"s": "zimnyaya-rezina-r14-na-lada-granta-shipovannaya", "t": "Зимняя резина R14 на Лада Гранта шипованная: выбор и советы", "i": "📁", "c": "granta"}, {"s": "zimnyaya-rezina-na-lada-granta-r14", "t": "Зимняя резина R14 на Лада Гранта: выбор и установка", "i": "📁", "c": "granta"}, {"s": "zimnyaya-rezina-205-50-17-dlya-lada-vesta-sw-kross", "t": "Зимняя резина 205 50 17 для Лада Веста SW Кросс: выбор и советы", "i": "📁", "c": "vesta"}, {"s": "zimnyaya-rezina-r14-na-lada-granta", "t": "Зимняя резина R14 на Лада Гранта: выбор, размеры, шипы или липучка", "i": "📁", "c": "granta"}]